		<stream name="da_state"
                        type="input;output"
                        filename_template="mpasout.$Y-$M-$D_$h.$m.$s.nc"
                        input_interval="initial_only"
                        output_interval="0_06:00:00"
                        immutable="true"
                        packages="jedi_da">

			<var_array name="scalars"/>
			<var name="initial_time"/>
			<var name="xtime"/>
                        <var name="Time"/>
			<var name="u"/>
			<var name="w"/>
                        <var name="rho_zz"/>
                        <var name="theta_m"/>
			<var name="rho"/>
			<var name="pressure_p"/>
			<var name="pressure_base"/>
			<var name="theta"/>
			<var name="relhum"/>
			<var name="rho_base"/>
			<var name="theta_base"/>
			<var name="uReconstructZonal"/>
			<var name="uReconstructMeridional"/>
                        <var name="circulation"/>
                        <var name="exner"/>
                        <var name="exner_base"/>
                        <var name="rtheta_base"/>
                        <var name="ru"/>
                        <var name="ru_p"/>
                        <var name="rw"/>
                        <var name="rw_p"/>
                        <var name="rtheta_p"/>
                        <var name="rho_p"/>
			<var name="surface_pressure"/>
#ifdef DO_PHYSICS
                        <var name="rainprod"/>
                        <var name="evapprod"/>
                        <var name="isltyp"/>
                        <var name="soilf"/>
                        <var name="ivgtyp"/>
                        <var name="landusef"/>
                        <var name="mminlu"/>
                        <var name="landmask"/>
                        <var name="shdmin"/>
                        <var name="shdmax"/>
                        <var name="snoalb"/>
                        <var name="albedo12m"/>
                        <var name="greenfrac"/>
                        <var name="lai12m"/>
			<var name="cldfrac"/>
			<var name="re_cloud" packages="mp_thompson_in;mp_wsm6_in;mp_tempo_in"/>
			<var name="re_ice" packages="mp_thompson_in;mp_wsm6_in;mp_tempo_in"/>
			<var name="re_snow" packages="mp_thompson_in;mp_wsm6_in;mp_tempo_in"/>
                        <var name="nwfa2d"/>
                        <var name="nifa2d"/>
                        <var name="nt_c"/>
                        <var name="mu_c"/>
                        <var name="tend_sfc_pressure"/>
                        <var name="rt_diabatic_tend"/>
                        <var name="nsteps_accum"/>
                        <var name="ndays_accum"/>
                        <var name="tlag"/>
                        <var name="tday_accum"/>
                        <var name="tyear_mean"/>
                        <var name="tyear_accum"/>
                        <var name="refl10cm"/>
			<var name="refl10cm_max"/>
			<var name="rainc"/>
			<var name="rainnc"/>
                        <var name="i_rainnc"/>
                        <var name="rainncv"/>
                        <var name="snowncv"/>
                        <var name="snownc"/>
                        <var name="graupelncv"/>
                        <var name="graupelnc"/>
                        <var name="sr"/>
                        <var name="i_rainc"/>
                        <var name="cuprec"/>
                        <var name="raincv"/>
                        <var name="nca"/>
                        <var name="cubot"/>
                        <var name="cutop"/>
                        <var name="w0avg"/>
                        <var name="qcg"/>
                        <var name="sh3d"/>
                        <var name="sm3d"/>
                        <var name="qke"/>
                        <var name="qke_adv"/>
                        <var name="cov"/>
                        <var name="qsq"/>
                        <var name="tsq"/>
                        <var name="tke_pbl"/>
                        <var name="wstar"/>
                        <var name="delta"/>
                        <var name="el_pbl"/>
                        <var name="edmf_a"/>
                        <var name="edmf_w"/>
                        <var name="edmf_qt"/>
                        <var name="edmf_qc"/>
                        <var name="edmf_thl"/>
                        <var name="edmf_ent"/>
                        <var name="sub_thl"/>
                        <var name="sub_qv"/>
                        <var name="det_thl"/>
                        <var name="det_qv"/>
                        <var name="cldfrac_bl"/>
                        <var name="qc_bl"/>
                        <var name="qi_bl"/>
                        <var name="ch"/>
                        <var name="kpbl"/>
                        <var name="hpbl"/>
                        <var name="hfx"/>
                        <var name="cldfrac_cu"/>
                        <var name="refl10cm_cu"/>
                        <var name="mol"/>
                        <var name="qfx"/>
                        <var name="qsfc"/>
                        <var name="ustm"/>
                        <var name="zol"/>
                        <var name="br"/>
                        <var name="cd"/>
                        <var name="cda"/>
                        <var name="chs"/>
                        <var name="chs2"/>
                        <var name="cqs2"/>
                        <var name="cqs"/>
                        <var name="ck"/>
                        <var name="cka"/>
                        <var name="cpm"/>
                        <var name="flhc"/>
                        <var name="flqc"/>
                        <var name="gz1oz0"/>
                        <var name="lh"/>
                        <var name="psim"/>
                        <var name="psih"/>
                        <var name="qgh"/>
                        <var name="regime"/>
                        <var name="rmol"/>
                        <var name="wspd"/>
                        <var name="fh"/>
                        <var name="fm"/>
                        <var name="th2m"/>
                        <var name="dusfcg"/>
                        <var name="dvsfcg"/>
                        <var name="dtaux3d"/>
                        <var name="dtauy3d"/>
                        <var name="rubldiff"/>
                        <var name="rvbldiff"/>
                        <var name="i_acswdnb"/>
                        <var name="i_acswdnbc"/>
                        <var name="i_acswdnt"/>
                        <var name="i_acswdntc"/>
                        <var name="i_acswupb"/>
                        <var name="i_acswupbc"/>
                        <var name="i_acswupt"/>
                        <var name="i_acswuptc"/>
                        <var name="acswdnb"/>
                        <var name="acswdnbc"/>
                        <var name="acswdnt"/>
                        <var name="acswdntc"/>
                        <var name="acswupb"/>
                        <var name="acswupbc"/>
                        <var name="acswupt"/>
                        <var name="acswuptc"/>
                        <var name="gsw"/>
                        <var name="i_aclwdnb"/>
                        <var name="i_aclwdnbc"/>
                        <var name="i_aclwdnt"/>
                        <var name="i_aclwdntc"/>
                        <var name="i_aclwupb"/>
                        <var name="i_aclwupbc"/>
                        <var name="i_aclwupt"/>
                        <var name="i_aclwuptc"/>
                        <var name="aclwdnb"/>
                        <var name="aclwdnbc"/>
                        <var name="aclwdnt"/>
                        <var name="aclwdntc"/>
                        <var name="aclwupb"/>
                        <var name="aclwupbc"/>
                        <var name="aclwupt"/>
                        <var name="aclwuptc"/>
                        <var name="glw"/>
                        <var name="o3clim"/>
                        <var name="o3vmr"/>
                        <var name="acsnom"/>
                        <var name="acsnow"/>
                        <var name="canwat"/>
                        <var name="chklowq"/>
                        <var name="grdflx"/>
                        <var name="noahres"/>
                        <var name="potevp"/>
                        <var name="sfcrunoff"/>
                        <var name="smstav"/>
                        <var name="smstot"/>
                        <var name="snopcx"/>
                        <var name="snotime"/>
                        <var name="sstsk"/>
                        <var name="sstsk_dtc"/>
                        <var name="sstsk_dtw"/>
                        <var name="udrunoff"/>
                        <var name="rhosnf"/>
                        <var name="precipfr"/>
                        <var name="qsg"/>
                        <var name="qvg"/>
                        <var name="dew"/>
                        <var name="soilt1"/>
                        <var name="tsnav"/>
                        <var name="acrunoff"/>
                        <var name="snowfallac"/>
                        <var name="smfr3d"/>
                        <var name="k22_shallow"/>
                        <var name="kbcon_shallow"/>
                        <var name="ktop_shallow"/>
                        <var name="ktop_deep"/>
                        <var name="xmb_total"/>
                        <var name="xmb_shallow"/>
                        <var name="qc_cu"/>
                        <var name="qi_cu"/>
                        <var name="rthmpten"/>
                        <var name="rqvmpten"/>
                        <var name="rqcmpten"/>
                        <var name="rqrmpten"/>
                        <var name="rqimpten"/>
                        <var name="rqsmpten"/>
                        <var name="rqgmpten"/>
                        <var name="rncmpten"/>
                        <var name="rnimpten"/>
                        <var name="rnrmpten"/>
                        <var name="rnifampten"/>
                        <var name="rnwfampten"/>
                        <var name="rthcuten"/>
                        <var name="rqvcuten"/>
                        <var name="rqccuten"/>
                        <var name="rqicuten"/>
                        <var name="rqrcuten"/>
                        <var name="rqscuten"/>
                        <var name="rqvdynten"/>
                        <var name="rthdynten"/>
                        <var name="rucuten"/>
                        <var name="rvcuten"/>
                        <var name="rublten"/>
                        <var name="rvblten"/>
                        <var name="rthblten"/>
                        <var name="rqvblten"/>
                        <var name="rqcblten"/>
                        <var name="rqiblten"/>
                        <var name="rqsblten"/>
                        <var name="rncblten"/>
                        <var name="rniblten"/>
                        <var name="rnifablten"/>
                        <var name="rnwfablten"/>
                        <var name="rthratensw"/>
                        <var name="rthratenlw"/>
                        <var name="vcpool" packages="cu_grell_freitas_in"/>
                        <var name="sub3d_rthcuten" packages="cu_grell_freitas_in"/>
                        <var name="sub3d_rqvcuten" packages="cu_grell_freitas_in"/>
                        <var name="sub3d_rucuten" packages="cu_grell_freitas_in"/>
                        <var name="sub3d_rvcuten" packages="cu_grell_freitas_in"/>
                        <var name="sigma_deep" packages="cu_grell_freitas_in"/>
                        <var name="smcrel"/>
                        <var name="t_oml"/>
                        <var name="t_oml_initial"/>
                        <var name="t_oml_200m_initial"/>
                        <var name="h_oml"/>
                        <var name="hu_oml"/>
                        <var name="hv_oml"/>
                        <var_struct name="diag_physics_noahmp"/>
			<var name="lai"/>
			<var name="isice_lu"/>
			<var name="iswater_lu"/>
			<var name="sfc_albbck"/>
			<var name="sfc_albedo"/>
			<var name="sfc_emibck"/>
			<var name="mavail"/>
			<var name="sfc_emiss"/>
			<var name="thc"/>
			<var name="ust"/>
			<var name="xicem"/>
			<var name="z0"/>
			<var name="znt"/>
			<var name="skintemp"/>
			<var name="snow"/>
			<var name="snowc"/>
			<var name="snowh"/>
			<var name="sst"/>
			<var name="tmn"/>
			<var name="vegfra"/>
			<var name="seaice"/>
			<var name="xice"/>
			<var name="xland"/>
			<var name="u10"/>
			<var name="v10"/>
			<var name="q2"/>
			<var name="t2m"/>
			<var name="precipw"/>
			<var name="dzs"/>
			<var name="zs"/>
			<var name="ter"/>
			<var name="sh2o"/>
			<var name="smois"/>
			<var name="tslb"/>
			<var name="h_oml_initial"/>
#endif
                </stream>
